models/__init__.py
models/routing_data_matrix.py
models/vrp_solver.py
routingoo/__init__.py
routingoo/routing_data_matrix.py
routingoo/vrp_solver.py
routing_ortools_osrm-1.0.1.dist-info/LICENSE
routing_ortools_osrm-1.0.1.dist-info/METADATA
routing_ortools_osrm-1.0.1.dist-info/WHEEL
routing_ortools_osrm-1.0.1.dist-info/top_level.txt
routing_ortools_osrm-1.0.1.dist-info/RECORD
