Metadata-Version: 2.1
Name: routing-ortools-osrm
Version: 1.0.1
Summary: Package to use Ortools combine with Osrm for routing
Home-page: https://gitlab.com/Tonow/routing-ortools-osrm
Author: Thomas Nowicki
Author-email: thomas.nowicki@camptocamp.com
License: Apache 2.0
Platform: UNKNOWN
Classifier: License :: OSI Approved :: Apache Software License
Classifier: Programming Language :: Python :: 3
Classifier: Programming Language :: Python :: 3.7
Requires-Python: >=3.6
Requires-Dist: ortools
Requires-Dist: gdal (==2.2)
Requires-Dist: pynominatim
Requires-Dist: osrm
Requires-Dist: matplotlib (==2.2.4)
